tsp_solver/__init__.py
tspsolver_ra_007-0.1.0.dist-info/METADATA
tspsolver_ra_007-0.1.0.dist-info/WHEEL
tspsolver_ra_007-0.1.0.dist-info/top_level.txt
tspsolver_ra_007-0.1.0.dist-info/RECORD
