Metadata-Version: 2.2
Name: TSPsolver_RA_007
Version: 0.1.0
Summary: A Python library for solving the Traveling Salesperson Problem (TSP) using various algorithms
Home-page: https://github.com/yourusername/TSPsolver_RA_007
Author: Rifath Anika
Author-email: rifathsultana.anika@students.cau.edu
Classifier: Programming Language :: Python :: 3
Classifier: License :: OSI Approved :: MIT License
Classifier: Operating System :: OS Independent
Requires-Python: >=3.6
Dynamic: author
Dynamic: author-email
Dynamic: classifier
Dynamic: home-page
Dynamic: requires-python
Dynamic: summary
